entertainment/__init__.py
entertainment/example.py
entertainment-0.0.1.dist-info/LICENSE
entertainment-0.0.1.dist-info/METADATA
entertainment-0.0.1.dist-info/WHEEL
entertainment-0.0.1.dist-info/top_level.txt
entertainment-0.0.1.dist-info/RECORD
