Metadata-Version: 2.1
Name: entertainment
Version: 0.0.1
Summary: Physics scripts
Home-page: https://github.com/joshuazlin/entertainment
Author: Joshua Lin
Author-email: joshua.z.lin@gmail.com
License: UNKNOWN
Project-URL: Bug Tracker, https://github.com/joshuazlin/entertainment/issues
Platform: UNKNOWN
Classifier: Programming Language :: Python :: 3
Classifier: License :: OSI Approved :: MIT License
Classifier: Operating System :: OS Independent
Requires-Python: >=3.6
License-File: LICENSE
